nexui/__init__.py
nexui/asgi.py
nexui/settings.py
nexui/urls.py
nexui/views.py
nexui/wsgi.py
nexui/templates/base.html
nexui/templates/form.html
nexui/templates/index.html
nexui/templates/index_old.html
nexui/templates/result.html
nexui/templates/components/button.html
nexui/templates/components/card.html
nexui/templates/components/input.html
nexui/templates/components/modal.html
nexui/templates/components/tabs.html
nexui/templates/components/toast.html
nexui/templatetags/__init__.py
nexui/templatetags/nexui_tags.py
nexui/templatetags/__pycache__/__init__.cpython-313.pyc
nexui/templatetags/__pycache__/custom_filters.cpython-313.pyc
nexui/templatetags/__pycache__/custom_tags.cpython-313.pyc
nexui/templatetags/__pycache__/nexui_tags.cpython-313.pyc
nexui/templatetags/__pycache__/nexui_tags_old_1.cpython-313.pyc
nexui-0.2.4.dist-info/LICENSE
nexui-0.2.4.dist-info/METADATA
nexui-0.2.4.dist-info/WHEEL
nexui-0.2.4.dist-info/top_level.txt
nexui-0.2.4.dist-info/RECORD
