Metadata-Version: 2.2
Name: nexui
Version: 0.2.4
Summary: Library of modern UI components with optional HTMX support
Author-email: Hugues Codeur <huguescodeur@gmail.com>
License: MIT
Project-URL: Homepage, https://github.com/huguescodeur/nexui
Project-URL: Issues, https://github.com/huguescodeur/nexui/issues
Classifier: Development Status :: 4 - Beta
Classifier: Framework :: Django
Classifier: Programming Language :: Python :: 3
Classifier: Programming Language :: Python :: 3.12
Classifier: Intended Audience :: Developers
Classifier: License :: OSI Approved :: MIT License
Classifier: Operating System :: OS Independent
Requires-Python: >=3.12
License-File: LICENSE
Requires-Dist: Django>=5.1
Requires-Dist: django-tailwind>=3.8.0
Provides-Extra: htmx
Requires-Dist: django-htmx>=1.17.2; extra == "htmx"
